setup.cfg
setup.py
CrudAlchemy.egg-info/PKG-INFO
CrudAlchemy.egg-info/SOURCES.txt
CrudAlchemy.egg-info/dependency_links.txt
CrudAlchemy.egg-info/requires.txt
CrudAlchemy.egg-info/top_level.txt
CrudAlchemy.egg-info/zip-safe
crudalchemy/__init__.py
crudalchemy/declarative.py
crudalchemy/utils.py