Metadata-Version: 1.1
Name: CrudAlchemy
Version: 0.2dev
Summary: Helper which encapsulates CRUD operations on SQLAlchemy models.
Home-page: https://github.com/stefanofontanelli/CrudAlchemy
Author: Stefano Fontanelli
Author-email: s.fontanelli@asidev.com
License: MIT
Keywords: crud sqlalchemy
Platform: UNKNOWN
Classifier: Development Status :: 3 - Alpha
Classifier: Intended Audience :: Developers
Classifier: Programming Language :: Python
Classifier: Programming Language :: Python :: 2.7
Classifier: License :: OSI Approved :: MIT License
Classifier: Operating System :: OS Independent
Classifier: Topic :: Database
